pybraces/__init__.py
pybraces/__main__.py
pybraces/pybraces.py
pybraces-0.2.0.data/scripts/pyb
pybraces-0.2.0.data/scripts/pybraces
pybraces-0.2.0.dist-info/LICENSE
pybraces-0.2.0.dist-info/METADATA
pybraces-0.2.0.dist-info/WHEEL
pybraces-0.2.0.dist-info/top_level.txt
pybraces-0.2.0.dist-info/RECORD
