Metadata-Version: 2.1
Name: pybraces
Version: 0.2.0
Summary: Python with braces
Home-page: https://github.com/ershov/pybraces
Author: Yury Ershov
License: GPL3
License-File: LICENSE
Requires-Dist: regex==2024.7.24
